gepyto/__init__.py
gepyto/reference.py
gepyto/settings.py
gepyto/version.py
gepyto/db/__init__.py
gepyto/db/appris.py
gepyto/db/ensembl.py
gepyto/db/index.py
gepyto/db/ucsc.py
gepyto/db/data/appris_data.principal.txt.gz
gepyto/formats/__init__.py
gepyto/formats/gtf.py
gepyto/formats/impute2.py
gepyto/formats/seqxml.py
gepyto/formats/wig.py
gepyto/structures/__init__.py
gepyto/structures/genes.py
gepyto/structures/region.py
gepyto/structures/sequences.py
gepyto/structures/variants.py
gepyto/tests/__init__.py
gepyto/tests/test_db_index.py
gepyto/tests/test_formats.py
gepyto/tests/test_reference.py
gepyto/tests/test_region.py
gepyto/tests/test_structures.py
gepyto/tests/test_variant_utils.py
gepyto/utils/__init__.py
gepyto/utils/genes.py
gepyto/utils/variants.py
gepyto/visualization/__init__.py
gepyto/visualization/ideograms.py
gepyto/visualization/region.py
gepyto-0.10.1.dist-info/DESCRIPTION.rst
gepyto-0.10.1.dist-info/METADATA
gepyto-0.10.1.dist-info/RECORD
gepyto-0.10.1.dist-info/WHEEL
gepyto-0.10.1.dist-info/metadata.json
gepyto-0.10.1.dist-info/pbr.json
gepyto-0.10.1.dist-info/top_level.txt
