Metadata-Version: 1.1
Name: gepyto
Version: 0.10.1
Summary: Utilities and tools to interface with genomic databases and to facilitate common bioinformatics tasks.
Home-page: https://github.com/legaultmarc/gepyto
Author: Marc-André Legault
Author-email: legaultmarc@gmail.com
License: CC BY-NC 4.0
Keywords: bioinformatics genomics impute2 genetics variant
Platform: UNKNOWN
Classifier: Development Status :: 4 - Beta
Classifier: Intended Audience :: Developers
Classifier: Intended Audience :: Science/Research
Classifier: Operating System :: Unix
Classifier: Operating System :: MacOS :: MacOS X
Classifier: Operating System :: POSIX :: Linux
Classifier: Programming Language :: Python
Classifier: Programming Language :: Python :: 2.7
Classifier: Programming Language :: Python :: 3.4
Classifier: Topic :: Scientific/Engineering :: Bio-Informatics
